{
    "versionCode":  343,
    "versionName":  "3.4.3",
    "apkUrl":  "https://raw.githubusercontent.com/Djmcarvalho/FutApp/main/dist/3.4.3/kickoff.apk",
    "apkSha256":  "83785537A54FACB5FC3DD096E2D3D4300DAF0F6C2994EE4E3D025D89A9B87A16",
    "releaseNotes":  "Melhora o aspeto dos diálogos mantendo o caminho Material estável da aplicação.",
    "changelog":  [
                      "Atualização para 3.4.3.",
                      "Os diálogos voltaram a usar o tema visual KickOff com o construtor Material estável.",
                      "Mantido o aspeto alinhado com a aplicação sem reintroduzir o cabeçalho custom instável.",
                      "Sem alterações na lógica de atualização OTA."
                  ]
}
