{
    "versionCode":  355,
    "versionName":  "3.5.5",
    "apkUrl":  "https://raw.githubusercontent.com/Djmcarvalho/FutApp/main/dist/3.5.5/kickoff.apk",
    "apkSha256":  "4A1204F71469543D9FB55A9B867397F16490D3E63988814442DE066C39238ED0",
    "releaseNotes":  "Reforço de testes: novo teste de integração ao CalendarSyncCoordinator para proteger o uso do catálogo local de competições guardado em SQLite.",
    "changelog":  [
                      "Atualização para 3.5.5.",
                      "Novo teste de integração ao CalendarSyncCoordinator.",
                      "Validação do uso preferencial do catálogo local de competições.",
                      "Maior proteção contra regressões no caminho otimizado de carregamento.",
                      "Build e testes mantidos sem regressões."
                  ]
}
